crewai_chat_ui/__init__.py
crewai_chat_ui/chat_handler.py
crewai_chat_ui/crew_loader.py
crewai_chat_ui/server.py
crewai_chat_ui/static/favicon.ico
crewai_chat_ui/static/index.html
crewai_chat_ui/static/scripts.js
crewai_chat_ui/static/styles.css
crewai_chat_ui-0.1.1.dist-info/METADATA
crewai_chat_ui-0.1.1.dist-info/WHEEL
crewai_chat_ui-0.1.1.dist-info/entry_points.txt
crewai_chat_ui-0.1.1.dist-info/top_level.txt
crewai_chat_ui-0.1.1.dist-info/RECORD
