Metadata-Version: 2.2
Name: crewai-chat-ui
Version: 0.1.1
Summary: Web UI for CrewAI chat functionality
Author-email: Lennex Zinyando <brizdigital@gmail.com>
Project-URL: Homepage, https://github.com/zinyando/crewai-chat-ui
Project-URL: Bug Tracker, https://github.com/zinyando/crewai-chat-ui/issues
Requires-Python: >=3.10
Requires-Dist: crewai>=0.105.0
Requires-Dist: flask>=2.0.0
Requires-Dist: click>=8.0.0
